[
    {
        "stepId": "STEP295",
        "stepName": "Url: WebTours",
        "infFile": "t1.inf",
        "time": 1601064736827
    },
    {
        "stepId": "STEP296",
        "stepName": "Submit Data: login.pl",
        "infFile": "t2.inf",
        "time": 1601064737220
    },
    {
        "stepId": "STEP297",
        "stepName": "Url: Search Flights Button",
        "infFile": "t3.inf",
        "time": 1601064737580
    },
    {
        "stepId": "STEP298",
        "stepName": "Submit Data: reservations.pl",
        "infFile": "t4.inf",
        "time": 1601064737899
    },
    {
        "stepId": "STEP299",
        "stepName": "Submit Data: reservations.pl_2",
        "infFile": "t5.inf",
        "time": 1601064738201
    },
    {
        "stepId": "STEP300",
        "stepName": "Submit Data: reservations.pl_3",
        "infFile": "t6.inf",
        "time": 1601064738536
    },
    {
        "stepId": "STEP301",
        "stepName": "Url: SignOff Button",
        "infFile": "t7.inf",
        "time": 1601064738877
    }
]